llm_council/__init__.py
llm_council/__main__.py
llm_council/assertions.py
llm_council/cli.py
llm_council/config.py
llm_council/contracts.py
llm_council/council.py
llm_council/discussion.py
llm_council/mcp_server.py
llm_council/mediator.py
llm_council/metrics.py
llm_council/models.py
llm_council/persistence.py
llm_council/personas.py
llm_council/providers.py
llm_council/schemas.py
llm_council/templates.py
llm_council/testing.py
llm_council/voting.py
llm_council_mcp-0.1.4.dist-info/METADATA
llm_council_mcp-0.1.4.dist-info/WHEEL
llm_council_mcp-0.1.4.dist-info/entry_points.txt
llm_council_mcp-0.1.4.dist-info/top_level.txt
llm_council_mcp-0.1.4.dist-info/RECORD
